Lyftrondata/AutomatedSchema.py
Lyftrondata/payasyougo.py
Lyftrondata/settings.py
Lyftrondata/pytransform/__init__.py
Lyftrondata/pytransform/_pytransform.so
Lyftrondata_Essentials_Linux_py3.9-0.0.1.dist-info/METADATA
Lyftrondata_Essentials_Linux_py3.9-0.0.1.dist-info/WHEEL
Lyftrondata_Essentials_Linux_py3.9-0.0.1.dist-info/top_level.txt
Lyftrondata_Essentials_Linux_py3.9-0.0.1.dist-info/RECORD
