Metadata-Version: 2.1
Name: Lyftrondata-Essentials-Linux-py3.9
Version: 0.0.1
Summary: Lyftrondata Essentials
Home-page: UNKNOWN
Author: Mohsin.Karim
Author-email: mohsin.karim@lyftrondata.com
License: UNKNOWN
Platform: UNKNOWN
Requires-Dist: PyQt5-Qt5 (==5.15.2)
Requires-Dist: PyQt5-sip (==12.9.0)
Requires-Dist: PyQt5 (==5.15.4)
Requires-Dist: SQLAlchemy (==1.4.23)
Requires-Dist: certifi (==2021.5.30)
Requires-Dist: charset-normalizer (==2.0.4)
Requires-Dist: getmac (==0.8.2)
Requires-Dist: greenlet (==1.1.1)
Requires-Dist: idna (==3.2)
Requires-Dist: numpy (==1.21.2)
Requires-Dist: pandas (==1.1.5)
Requires-Dist: psycopg2-binary (==2.9.1)
Requires-Dist: pyarmor (==6.8.1)
Requires-Dist: pycrypto (==2.6.1)
Requires-Dist: pycryptodome (==3.14.1)
Requires-Dist: python-dateutil (==2.8.2)
Requires-Dist: pytz (==2021.1)
Requires-Dist: requests (==2.26.0)
Requires-Dist: schedule (==1.1.0)
Requires-Dist: six (==1.16.0)
Requires-Dist: sqlparse (==0.4.1)
Requires-Dist: urllib3 (==1.26.6)
